README.md
setup.py
fimaster.egg-info/PKG-INFO
fimaster.egg-info/SOURCES.txt
fimaster.egg-info/dependency_links.txt
fimaster.egg-info/requires.txt
fimaster.egg-info/top_level.txt
src/fimaster/__init__.py
src/fimaster/data_api/__init__.py
src/fimaster/data_api/ust_yield_curve.py
src/fimaster/valuation/__init__.py
src/fimaster/valuation/simple_yield_calculator.py