Metadata-Version: 2.1
Name: fimaster
Version: 0.0.0.5
Summary: A python library for fixed-income data and valuation.
Home-page: https://github.com/gavinz0228/fi-master
Author: Gavin Zhang
Author-email: gavinz0228@gmail.com
License: UNKNOWN
Platform: UNKNOWN
Classifier: Programming Language :: Python :: 3
Classifier: License :: OSI Approved :: MIT License
Classifier: Operating System :: MacOS :: MacOS X
Classifier: Operating System :: Microsoft :: Windows
Classifier: Operating System :: POSIX
